moodle_mcp/__init__.py
moodle_mcp/api.py
moodle_mcp/logger.py
moodle_mcp/moodle.py
moodle_mcp/server.py
moodle_mcp/utils.py
moodle_mcp-0.1.0.dist-info/METADATA
moodle_mcp-0.1.0.dist-info/WHEEL
moodle_mcp-0.1.0.dist-info/entry_points.txt
moodle_mcp-0.1.0.dist-info/top_level.txt
moodle_mcp-0.1.0.dist-info/RECORD
